htc_utils/__init__.py
htc_utils/version.py
htc_utils/CLI/__init__.py
htc_utils/CLI/batch.py
htc_utils/CLI/split.py
htc_utils/CLI/wrap.py
htc_utils/bindings/__init__.py
htc_utils/bindings/job.py
htc_utils/bindings/submit.py
htc_utils/bindings/wait.py
htc_utils-0.1.2.data/scripts/condor_batch
htc_utils-0.1.2.data/scripts/condor_split
htc_utils-0.1.2.data/scripts/condor_wrap
htc_utils-0.1.2.dist-info/COPYING
htc_utils-0.1.2.dist-info/METADATA
htc_utils-0.1.2.dist-info/WHEEL
htc_utils-0.1.2.dist-info/top_level.txt
htc_utils-0.1.2.dist-info/RECORD
